sine.alarmclock-0.7.0-py2.7-nspkg.pth
sine/alarmclock/SysTrayIcon.py
sine/alarmclock/TrayMsg.py
sine/alarmclock/__init__.py
sine/alarmclock/__main__.py
sine/alarmclock/__version__.py
sine/alarmclock/alarm.ico.default
sine/alarmclock/app.py
sine/alarmclock/beep.properties.default
sine/alarmclock/clock.ico.default
sine/alarmclock/clock.properties.default
sine/alarmclock/date.properties.default
sine/alarmclock/entity.py
sine/alarmclock/exception.py
sine/alarmclock/formatter.py
sine/alarmclock/globalData.py
sine/alarmclock/initUtil.py
sine/alarmclock/manager.py
sine/alarmclock/msg.ico.default
sine/alarmclock/mydatetime.py
sine/alarmclock/mylogging.py
sine/alarmclock/parsing.py
sine/alarmclock/player.py
sine/alarmclock/quiet.ico.default
sine/alarmclock/time.properties.default
sine/alarmclock/trayIcon.py
sine/alarmclock/userInterface.py
sine/alarmclock/winUtil.py
sine.alarmclock-0.7.0.dist-info/DESCRIPTION.rst
sine.alarmclock-0.7.0.dist-info/METADATA
sine.alarmclock-0.7.0.dist-info/RECORD
sine.alarmclock-0.7.0.dist-info/WHEEL
sine.alarmclock-0.7.0.dist-info/metadata.json
sine.alarmclock-0.7.0.dist-info/namespace_packages.txt
sine.alarmclock-0.7.0.dist-info/top_level.txt
