Metadata-Version: 2.0
Name: sine.alarmclock
Version: 0.7.0
Summary: Windows command line alarm clock (python2)
Home-page: https://github.com/SineObama/AlarmClock
Author: Xian Zheng
Author-email: 714186139@qq.com
License: MIT
Platform: UNKNOWN
Classifier: License :: OSI Approved :: MIT License
Classifier: Programming Language :: Python
Classifier: Programming Language :: Python :: 2.7
Classifier: Programming Language :: Python :: Implementation :: CPython
Classifier: Programming Language :: Python :: Implementation :: PyPy
Classifier: Operating System :: Microsoft :: Windows
Requires-Python: >=2.7.0
Requires-Dist: plone.synchronize
Requires-Dist: sine.event
Requires-Dist: sine.path
Requires-Dist: sine.properties
Requires-Dist: sine.threads (>=0.1.6)
